{
  "title": "AI 精选周报",
  "description": "聚合多个科技源，使用 AI 生成摘要后的精华内容",
  "updated": "2026-04-04T20:40:49.019Z",
  "items": [
    {
      "title": "千里科技 2025 年营收 99.99 亿元同比增长 42%，AI 转型与汽车业务双轮驱动",
      "link": "https://www.ithome.com/0/936/055.htm",
      "summary": "<p data-vmark=\"8175\" style=\"text-align: left;\">IT之家 4 月 4 日消息，千里科技于 4 月 3 日发布 2025 年年度报告。报告显示，2025 年公司实现营业收入 99.99 亿元，同比增长 42.13%，主要系汽车业务、摩托车业务销量增长，带动收入增加；实现归属于上市公司股东的净利润 0.84 亿元，<strong>同比增长 110.93%<...",
      "pubDate": "2026-04-04T14:17:00.000Z",
      "source": "IT之家"
    }
  ]
}