{
  "title": "AI 精选周报",
  "description": "聚合多个科技源，使用 AI 生成摘要后的精华内容",
  "updated": "2026-04-10T06:02:45.976Z",
  "items": [
    {
      "title": "谷歌 Gemini AI 解锁新技能：生成交互式图表和 3D 模型",
      "link": "https://www.ithome.com/0/937/774.htm",
      "summary": "<p data-vmark=\"bc12\">IT之家 4 月 10 日消息，谷歌正不断强化 Gemini 的可视化能力，当地时间 4 月 9 日，Gemini 的最新更新带来了交互式 3D 模拟与模型功能，用户通过简单提示即可生成动态内容。</p><p data-vmark=\"615f\">据外媒 Neowin 报道，相比过去以文本和静态图示为主的回答方式，Gemini 在更新后能够提供“可操作的模拟...",
      "pubDate": "2026-04-10T05:51:28.000Z",
      "source": "IT之家"
    }
  ]
}